easytwo.py
easytwo-0.2.0.dist-info/DESCRIPTION.rst
easytwo-0.2.0.dist-info/METADATA
easytwo-0.2.0.dist-info/RECORD
easytwo-0.2.0.dist-info/WHEEL
easytwo-0.2.0.dist-info/entry_points.txt
easytwo-0.2.0.dist-info/metadata.json
easytwo-0.2.0.dist-info/top_level.txt
