Metadata-Version: 2.0
Name: easytwo
Version: 0.2.0
Summary: Easy EC2 Queries.
Home-page: http://github.com/spappier/easytwo
Author: Santiago Pappier
Author-email: spappier@gmail.com
License: MIT
Keywords: aws ec2
Platform: UNKNOWN
Classifier: Development Status :: 4 - Beta
Classifier: Intended Audience :: Developers
Classifier: Topic :: Utilities
Classifier: License :: OSI Approved :: MIT License
Classifier: Programming Language :: Python :: 2.7
Classifier: Programming Language :: Python :: 3.5
Classifier: Programming Language :: Python :: 3.6
Requires-Dist: boto3 (>=1.4)
Requires-Dist: click (>=6.7)
